celery_prometheus_exporter.py
celery_prometheus_exporter-1.7.0.dist-info/LICENSE.txt
celery_prometheus_exporter-1.7.0.dist-info/METADATA
celery_prometheus_exporter-1.7.0.dist-info/WHEEL
celery_prometheus_exporter-1.7.0.dist-info/entry_points.txt
celery_prometheus_exporter-1.7.0.dist-info/top_level.txt
celery_prometheus_exporter-1.7.0.dist-info/RECORD
