Metadata-Version: 2.1
Name: celery-prometheus-exporter
Version: 1.7.0
Summary: Simple Prometheus metrics exporter for Celery
Home-page: https://github.com/zerok/celery-prometheus-exporter
Author: Horst Gutmann
Author-email: horst@zerokspot.com
License: MIT
Platform: UNKNOWN
Classifier: Development Status :: 3 - Alpha
Classifier: Environment :: Console
Classifier: License :: OSI Approved :: MIT License
Classifier: Programming Language :: Python :: 3.5
Classifier: Programming Language :: Python :: 3 :: Only
Requires-Dist: celery (>=3)
Requires-Dist: prometheus-client (>=0.0.20)
